{
  "查询条件": {
    "出发地": "南宁",
    "目的地": "广州"
  },
  "航班数量": 7,
  "航班列表": [
    {
      "出发地": "南宁",
      "目的地": "广州",
      "航班类型": "国内航班",
      "航班日期": "2025-12-16",
      "航班代码": "CZ3291",
      "价格": "330"
    },
    {
      "出发地": "南宁",
      "目的地": "广州",
      "航班类型": "国内航班",
      "航班日期": "2025-12-21",
      "航班代码": "MF4164",
      "价格": "370"
    },
    {
      "出发地": "南宁",
      "目的地": "广州",
      "航班类型": "国内航班",
      "航班日期": "2025-12-22",
      "航班代码": "3U8138/3U8749",
      "价格": "499"
    },
    {
      "出发地": "南宁",
      "目的地": "广州",
      "航班类型": "国内航班",
      "航班日期": "2025-12-25",
      "航班代码": "MF4164",
      "价格": "330"
    },
    {
      "出发地": "南宁",
      "目的地": "广州",
      "航班类型": "国内航班",
      "航班日期": "2025-12-30",
      "航班代码": "MF4164",
      "价格": "330"
    },
    {
      "出发地": "南宁",
      "目的地": "广州",
      "航班类型": "国内航班",
      "航班日期": "2025-12-31",
      "航班代码": "MF4164",
      "价格": "330"
    },
    {
      "出发地": "南宁",
      "目的地": "广州",
      "航班类型": "国内航班",
      "航班日期": "2026-02-05",
      "航班代码": "CZ3295",
      "价格": "450"
    }
  ]
}