{
  "查询条件": {
    "出发地": "上海",
    "目的地": "太原"
  },
  "航班数量": 39,
  "航班列表": [
    {
      "出发地": "上海",
      "目的地": "太原",
      "航班类型": "国内航班",
      "航班日期": "2025-12-16",
      "航班代码": "SC4608/SC4923",
      "价格": "400"
    },
    {
      "出发地": "上海",
      "目的地": "太原",
      "航班类型": "国内航班",
      "航班日期": "2025-12-17",
      "航班代码": "CZ142",
      "价格": "350"
    },
    {
      "出发地": "上海",
      "目的地": "太原",
      "航班类型": "国内航班",
      "航班日期": "2025-12-18",
      "航班代码": "HO1239",
      "价格": "287"
    },
    {
      "出发地": "上海",
      "目的地": "太原",
      "航班类型": "国内航班",
      "航班日期": "2025-12-19",
      "航班代码": "CA8567/CA8597",
      "价格": "396"
    },
    {
      "出发地": "上海",
      "目的地": "太原",
      "航班类型": "国内航班",
      "航班日期": "2025-12-20",
      "航班代码": "MU2514/MU6352",
      "价格": "391"
    },
    {
      "出发地": "上海",
      "目的地": "太原",
      "航班类型": "国内航班",
      "航班日期": "2025-12-21",
      "航班代码": "MU2882/MU6942",
      "价格": "394"
    },
    {
      "出发地": "上海",
      "目的地": "太原",
      "航班类型": "国内航班",
      "航班日期": "2025-12-22",
      "航班代码": "CA8567/CA8597",
      "价格": "399"
    },
    {
      "出发地": "上海",
      "目的地": "太原",
      "航班类型": "国内航班",
      "航班日期": "2025-12-23",
      "航班代码": "MU6375/MU6625",
      "价格": "394"
    },
    {
      "出发地": "上海",
      "目的地": "太原",
      "航班类型": "国内航班",
      "航班日期": "2025-12-24",
      "航班代码": "MU2524/MU2438",
      "价格": "371"
    },
    {
      "出发地": "上海",
      "目的地": "太原",
      "航班类型": "国内航班",
      "航班日期": "2025-12-25",
      "航班代码": "MU2882/MU2703",
      "价格": "369"
    },
    {
      "出发地": "上海",
      "目的地": "太原",
      "航班类型": "国内航班",
      "航班日期": "2025-12-26",
      "航班代码": "MU2882/MU2703",
      "价格": "394"
    },
    {
      "出发地": "上海",
      "目的地": "太原",
      "航班类型": "国内航班",
      "航班日期": "2025-12-27",
      "航班代码": "MU2544/MU6352",
      "价格": "380"
    },
    {
      "出发地": "上海",
      "目的地": "太原",
      "航班类型": "国内航班",
      "航班日期": "2025-12-28",
      "航班代码": "CA8567/CA8597",
      "价格": "396"
    },
    {
      "出发地": "上海",
      "目的地": "太原",
      "航班类型": "国内航班",
      "航班日期": "2025-12-29",
      "航班代码": "MU2882/MU2703",
      "价格": "394"
    },
    {
      "出发地": "上海",
      "目的地": "太原",
      "航班类型": "国内航班",
      "航班日期": "2025-12-30",
      "航班代码": "SC4604/SC4923",
      "价格": "400"
    },
    {
      "出发地": "上海",
      "目的地": "太原",
      "航班类型": "国内航班",
      "航班日期": "2025-12-31",
      "航班代码": "CA8567/CA8597",
      "价格": "396"
    },
    {
      "出发地": "上海",
      "目的地": "太原",
      "航班类型": "国内航班",
      "航班日期": "2026-01-01",
      "航班代码": "MU5219",
      "价格": "382"
    },
    {
      "出发地": "上海",
      "目的地": "太原",
      "航班类型": "国内航班",
      "航班日期": "2026-01-02",
      "航班代码": "HO1239",
      "价格": "350"
    },
    {
      "出发地": "上海",
      "目的地": "太原",
      "航班类型": "国内航班",
      "航班日期": "2026-01-03",
      "航班代码": "HO1239",
      "价格": "350"
    },
    {
      "出发地": "上海",
      "目的地": "太原",
      "航班类型": "国内航班",
      "航班日期": "2026-01-06",
      "航班代码": "MU5219",
      "价格": "354"
    },
    {
      "出发地": "上海",
      "目的地": "太原",
      "航班类型": "国内航班",
      "航班日期": "2026-01-15",
      "航班代码": "MU5219",
      "价格": "382"
    },
    {
      "出发地": "上海",
      "目的地": "太原",
      "航班类型": "国内航班",
      "航班日期": "2026-01-16",
      "航班代码": "FM9139",
      "价格": "400"
    },
    {
      "出发地": "上海",
      "目的地": "太原",
      "航班类型": "国内航班",
      "航班日期": "2026-01-30",
      "航班代码": "MU2882/MU2703",
      "价格": "427"
    },
    {
      "出发地": "上海",
      "目的地": "太原",
      "航班类型": "国内航班",
      "航班日期": "2026-01-31",
      "航班代码": "MU5299/MU9908",
      "价格": "530"
    },
    {
      "出发地": "上海",
      "目的地": "太原",
      "航班类型": "国内航班",
      "航班日期": "2026-02-01",
      "航班代码": "MU2544/MU6352",
      "价格": "635"
    },
    {
      "出发地": "上海",
      "目的地": "太原",
      "航班类型": "国内航班",
      "航班日期": "2026-02-07",
      "航班代码": "MU5209",
      "价格": "857"
    },
    {
      "出发地": "上海",
      "目的地": "太原",
      "航班类型": "国内航班",
      "航班日期": "2026-02-09",
      "航班代码": "FM9111/CA2925",
      "价格": "943"
    },
    {
      "出发地": "上海",
      "目的地": "太原",
      "航班类型": "国内航班",
      "航班日期": "2026-02-10",
      "航班代码": "MU5227/CA2925",
      "价格": "942"
    },
    {
      "出发地": "上海",
      "目的地": "太原",
      "航班类型": "国内航班",
      "航班日期": "2026-02-12",
      "航班代码": "MU8323",
      "价格": "1420"
    },
    {
      "出发地": "上海",
      "目的地": "太原",
      "航班类型": "国内航班",
      "航班日期": "2026-02-13",
      "航班代码": "MU8323",
      "价格": "1410"
    },
    {
      "出发地": "上海",
      "目的地": "太原",
      "航班类型": "国内航班",
      "航班日期": "2026-02-14",
      "航班代码": "CA2824/CA2925",
      "价格": "1300"
    },
    {
      "出发地": "上海",
      "目的地": "太原",
      "航班类型": "国内航班",
      "航班日期": "2026-02-15",
      "航班代码": "CA2824/CA2925",
      "价格": "1300"
    },
    {
      "出发地": "上海",
      "目的地": "太原",
      "航班类型": "国内航班",
      "航班日期": "2026-02-18",
      "航班代码": "MU5219",
      "价格": "630"
    },
    {
      "出发地": "上海",
      "目的地": "太原",
      "航班类型": "国内航班",
      "航班日期": "2026-02-19",
      "航班代码": "HO1239",
      "价格": "480"
    },
    {
      "出发地": "上海",
      "目的地": "太原",
      "航班类型": "国内航班",
      "航班日期": "2026-02-20",
      "航班代码": "MU3732",
      "价格": "480"
    },
    {
      "出发地": "上海",
      "目的地": "太原",
      "航班类型": "国内航班",
      "航班日期": "2026-02-21",
      "航班代码": "FM9139",
      "价格": "468"
    },
    {
      "出发地": "上海",
      "目的地": "太原",
      "航班类型": "国内航班",
      "航班日期": "2026-02-22",
      "航班代码": "HO1239",
      "价格": "480"
    },
    {
      "出发地": "上海",
      "目的地": "太原",
      "航班类型": "国内航班",
      "航班日期": "2026-02-23",
      "航班代码": "MU3732",
      "价格": "480"
    },
    {
      "出发地": "上海",
      "目的地": "太原",
      "航班类型": "国内航班",
      "航班日期": "2026-02-26",
      "航班代码": "9C8733",
      "价格": "400"
    }
  ]
}