{
  "查询条件": {
    "出发地": "成都",
    "目的地": "天津"
  },
  "航班数量": 42,
  "航班列表": [
    {
      "出发地": "成都",
      "目的地": "天津",
      "航班类型": "国内航班",
      "航班日期": "2025-12-16",
      "航班代码": "MF8442/MF8125",
      "价格": "390"
    },
    {
      "出发地": "成都",
      "目的地": "天津",
      "航班类型": "国内航班",
      "航班日期": "2025-12-17",
      "航班代码": "3U8861",
      "价格": "330"
    },
    {
      "出发地": "成都",
      "目的地": "天津",
      "航班类型": "国内航班",
      "航班日期": "2025-12-18",
      "航班代码": "3U8861",
      "价格": "330"
    },
    {
      "出发地": "成都",
      "目的地": "天津",
      "航班类型": "国内航班",
      "航班日期": "2025-12-19",
      "航班代码": "8L9645",
      "价格": "320"
    },
    {
      "出发地": "成都",
      "目的地": "天津",
      "航班类型": "国内航班",
      "航班日期": "2025-12-20",
      "航班代码": "8L9645",
      "价格": "350"
    },
    {
      "出发地": "成都",
      "目的地": "天津",
      "航班类型": "国内航班",
      "航班日期": "2025-12-21",
      "航班代码": "3U8861",
      "价格": "330"
    },
    {
      "出发地": "成都",
      "目的地": "天津",
      "航班类型": "国内航班",
      "航班日期": "2025-12-22",
      "航班代码": "8L9645",
      "价格": "350"
    },
    {
      "出发地": "成都",
      "目的地": "天津",
      "航班类型": "国内航班",
      "航班日期": "2025-12-23",
      "航班代码": "CA8296/CA2842",
      "价格": "499"
    },
    {
      "出发地": "成都",
      "目的地": "天津",
      "航班类型": "国内航班",
      "航班日期": "2025-12-24",
      "航班代码": "8L9645",
      "价格": "270"
    },
    {
      "出发地": "成都",
      "目的地": "天津",
      "航班类型": "国内航班",
      "航班日期": "2025-12-25",
      "航班代码": "G52563P",
      "价格": "380"
    },
    {
      "出发地": "成都",
      "目的地": "天津",
      "航班类型": "国内航班",
      "航班日期": "2025-12-26",
      "航班代码": "8L9645",
      "价格": "342"
    },
    {
      "出发地": "成都",
      "目的地": "天津",
      "航班类型": "国内航班",
      "航班日期": "2025-12-27",
      "航班代码": "G52563P",
      "价格": "380"
    },
    {
      "出发地": "成都",
      "目的地": "天津",
      "航班类型": "国内航班",
      "航班日期": "2025-12-28",
      "航班代码": "G52563P",
      "价格": "380"
    },
    {
      "出发地": "成都",
      "目的地": "天津",
      "航班类型": "国内航班",
      "航班日期": "2025-12-29",
      "航班代码": "G52563P",
      "价格": "380"
    },
    {
      "出发地": "成都",
      "目的地": "天津",
      "航班类型": "国内航班",
      "航班日期": "2025-12-30",
      "航班代码": "MU5418/MU8571",
      "价格": "400"
    },
    {
      "出发地": "成都",
      "目的地": "天津",
      "航班类型": "国内航班",
      "航班日期": "2025-12-31",
      "航班代码": "8L9645",
      "价格": "420"
    },
    {
      "出发地": "成都",
      "目的地": "天津",
      "航班类型": "国内航班",
      "航班日期": "2026-01-01",
      "航班代码": "8L9645",
      "价格": "437"
    },
    {
      "出发地": "成都",
      "目的地": "天津",
      "航班类型": "国内航班",
      "航班日期": "2026-01-02",
      "航班代码": "TV7409",
      "价格": "350"
    },
    {
      "出发地": "成都",
      "目的地": "天津",
      "航班类型": "国内航班",
      "航班日期": "2026-01-03",
      "航班代码": "MU2471/MU6259",
      "价格": "470"
    },
    {
      "出发地": "成都",
      "目的地": "天津",
      "航班类型": "国内航班",
      "航班日期": "2026-01-04",
      "航班代码": "8L9645",
      "价格": "418"
    },
    {
      "出发地": "成都",
      "目的地": "天津",
      "航班类型": "国内航班",
      "航班日期": "2026-01-07",
      "航班代码": "8L9645",
      "价格": "333"
    },
    {
      "出发地": "成都",
      "目的地": "天津",
      "航班类型": "国内航班",
      "航班日期": "2026-01-14",
      "航班代码": "8L9645",
      "价格": "360"
    },
    {
      "出发地": "成都",
      "目的地": "天津",
      "航班类型": "国内航班",
      "航班日期": "2026-01-22",
      "航班代码": "MU2525/MU2483",
      "价格": "520"
    },
    {
      "出发地": "成都",
      "目的地": "天津",
      "航班类型": "国内航班",
      "航班日期": "2026-01-23",
      "航班代码": "8L9645",
      "价格": "450"
    },
    {
      "出发地": "成都",
      "目的地": "天津",
      "航班类型": "国内航班",
      "航班日期": "2026-01-25",
      "航班代码": "TV7409",
      "价格": "600"
    },
    {
      "出发地": "成都",
      "目的地": "天津",
      "航班类型": "国内航班",
      "航班日期": "2026-01-26",
      "航班代码": "8L9645",
      "价格": "450"
    },
    {
      "出发地": "成都",
      "目的地": "天津",
      "航班类型": "国内航班",
      "航班日期": "2026-01-30",
      "航班代码": "MU2471/MU6259",
      "价格": "470"
    },
    {
      "出发地": "成都",
      "目的地": "天津",
      "航班类型": "国内航班",
      "航班日期": "2026-02-02",
      "航班代码": "TV7409",
      "价格": "680"
    },
    {
      "出发地": "成都",
      "目的地": "天津",
      "航班类型": "国内航班",
      "航班日期": "2026-02-06",
      "航班代码": "MU2525/MU2483",
      "价格": "520"
    },
    {
      "出发地": "成都",
      "目的地": "天津",
      "航班类型": "国内航班",
      "航班日期": "2026-02-07",
      "航班代码": "CA2583/CA2928",
      "价格": "600"
    },
    {
      "出发地": "成都",
      "目的地": "天津",
      "航班类型": "国内航班",
      "航班日期": "2026-02-08",
      "航班代码": "TV7409",
      "价格": "680"
    },
    {
      "出发地": "成都",
      "目的地": "天津",
      "航班类型": "国内航班",
      "航班日期": "2026-02-13",
      "航班代码": "TV7409",
      "价格": "760"
    },
    {
      "出发地": "成都",
      "目的地": "天津",
      "航班类型": "国内航班",
      "航班日期": "2026-02-14",
      "航班代码": "MU2654/MU2483",
      "价格": "520"
    },
    {
      "出发地": "成都",
      "目的地": "天津",
      "航班类型": "国内航班",
      "航班日期": "2026-02-15",
      "航班代码": "CA2583/CA2928",
      "价格": "600"
    },
    {
      "出发地": "成都",
      "目的地": "天津",
      "航班类型": "国内航班",
      "航班日期": "2026-02-16",
      "航班代码": "MU2525/MU2483",
      "价格": "520"
    },
    {
      "出发地": "成都",
      "目的地": "天津",
      "航班类型": "国内航班",
      "航班日期": "2026-02-18",
      "航班代码": "MU2525/MU2483",
      "价格": "520"
    },
    {
      "出发地": "成都",
      "目的地": "天津",
      "航班类型": "国内航班",
      "航班日期": "2026-02-19",
      "航班代码": "CA2583/CA2928",
      "价格": "600"
    },
    {
      "出发地": "成都",
      "目的地": "天津",
      "航班类型": "国内航班",
      "航班日期": "2026-02-22",
      "航班代码": "CA2958",
      "价格": "1580"
    },
    {
      "出发地": "成都",
      "目的地": "天津",
      "航班类型": "国内航班",
      "航班日期": "2026-03-27",
      "航班代码": "CA2619/CA8225",
      "价格": "550"
    },
    {
      "出发地": "成都",
      "目的地": "天津",
      "航班类型": "国内航班",
      "航班日期": "2026-03-28",
      "航班代码": "CA2619/CA8225",
      "价格": "550"
    },
    {
      "出发地": "成都",
      "目的地": "天津",
      "航班类型": "国内航班",
      "航班日期": "2026-03-29",
      "航班代码": "CA2559/CA2878",
      "价格": "550"
    },
    {
      "出发地": "成都",
      "目的地": "天津",
      "航班类型": "国内航班",
      "航班日期": "2026-03-30",
      "航班代码": "CA2559/CA2878",
      "价格": "550"
    }
  ]
}